open_source_insights_api/__init__.py
open_source_insights_api/cli.py
open_source_insights_api/os_insights.py
open_source_insights_api-0.1.16.dist-info/LICENSE
open_source_insights_api-0.1.16.dist-info/METADATA
open_source_insights_api-0.1.16.dist-info/WHEEL
open_source_insights_api-0.1.16.dist-info/entry_points.txt
open_source_insights_api-0.1.16.dist-info/RECORD
