Metadata-Version: 2.1
Name: open-source-insights-api
Version: 0.1.16
Summary: Library to consume project Open Source Insights Project from Google
License: MIT
Author: Cristiano Henrique
Author-email: cristianovisk@gmail.com
Requires-Python: >=3.10,<3.13
Classifier: Development Status :: 5 - Production/Stable
Classifier: Environment :: Console
Classifier: License :: OSI Approved :: MIT License
Classifier: Natural Language :: Portuguese (Brazilian)
Classifier: Programming Language :: Python :: 3
Classifier: Programming Language :: Python :: 3.10
Classifier: Programming Language :: Python :: 3.11
Classifier: Topic :: Internet
Requires-Dist: httpx (>=0.25.0,<0.26.0)
Requires-Dist: openpyxl (>=3.1.2,<4.0.0)
Requires-Dist: packageurl-python (>=0.11.2,<0.12.0)
Requires-Dist: pandas (>=2.1.1,<3.0.0)
Requires-Dist: rich (>=13.4.2,<14.0.0)
Project-URL: Bug Tracker, https://github.com/cristianovisk/open_source_insights_api/issues
Project-URL: Código, https://github.com/cristianovisk/open_source_insights_api
Project-URL: Documentação, https://github.com/cristianovisk/open_source_insights_api/blob/main/README.md
